motley_cue/__init__.py
motley_cue/__main__.py
motley_cue/api.py
motley_cue/admin/__init__.py
motley_cue/admin/admin.py
motley_cue/mapper/__init__.py
motley_cue/mapper/config.py
motley_cue/user/__init__.py
motley_cue/user/user.py
motley_cue-0.0.13.data/data/etc/motley_cue/feudal_adapter.conf
motley_cue-0.0.13.data/data/etc/motley_cue/gunicorn.conf.py
motley_cue-0.0.13.data/data/etc/motley_cue/motley_cue.conf
motley_cue-0.0.13.data/data/etc/motley_cue/motley_cue.env
motley_cue-0.0.13.data/data/etc/nginx/nginx.motley_cue
motley_cue-0.0.13.data/data/etc/systemd/system/motley-cue.service
motley_cue-0.0.13.dist-info/LICENSE
motley_cue-0.0.13.dist-info/METADATA
motley_cue-0.0.13.dist-info/WHEEL
motley_cue-0.0.13.dist-info/entry_points.txt
motley_cue-0.0.13.dist-info/pbr.json
motley_cue-0.0.13.dist-info/top_level.txt
motley_cue-0.0.13.dist-info/RECORD
